[ "com.bbn.akbc.neolearnit.scoring.TargetAndScoreTables", {
  "startDate" : [ "java.util.Date", 1597957512209 ],
  "seedScores" : [ "com.bbn.akbc.neolearnit.scoring.tables.SeedScoreTable", {
    "data" : [ "com.bbn.akbc.neolearnit.storage.EfficientMapDataStore", {
      "keyList" : [ "java.util.ArrayList", [ ] ],
      "valList" : [ "java.util.ArrayList", [ ] ],
      "entries" : [ "java.util.ArrayList", [ ] ]
    } ],
    "iteration" : 32
  } ],
  "patternScores" : [ "com.bbn.akbc.neolearnit.scoring.tables.PatternScoreTable", {
    "data" : [ "com.bbn.akbc.neolearnit.storage.EfficientMapDataStore", {
      "keyList" : [ "java.util.ArrayList", [ ] ],
      "valList" : [ "java.util.ArrayList", [ ] ],
      "entries" : [ "java.util.ArrayList", [ ] ]
    } ],
    "iteration" : 32
  } ],
  "tripleScores" : [ "com.bbn.akbc.neolearnit.scoring.tables.TripleScoreTable", {
    "data" : [ "com.bbn.akbc.neolearnit.storage.EfficientMapDataStore", {
      "keyList" : [ "java.util.ArrayList", [ ] ],
      "valList" : [ "java.util.ArrayList", [ ] ],
      "entries" : [ "java.util.ArrayList", [ ] ]
    } ],
    "iteration" : 0
  } ],
  "iteration" : 32,
  "goodSeedPrior" : 0.001,
  "totalConfidenceDenominator" : 0.0,
  "stage" : "initial",
  "params" : null,
  "experimentName" : "default"
} ]