[ "com.bbn.akbc.neolearnit.scoring.TargetAndScoreTables", {
  "startDate" : [ "java.util.Date", 1597957512246 ],
  "seedScores" : [ "com.bbn.akbc.neolearnit.scoring.tables.SeedScoreTable", {
    "data" : [ "com.bbn.akbc.neolearnit.storage.EfficientMapDataStore", {
      "keyList" : [ "java.util.ArrayList", [ ] ],
      "valList" : [ "java.util.ArrayList", [ ] ],
      "entries" : [ "java.util.ArrayList", [ ] ]
    } ],
    "iteration" : 32
  } ],
  "patternScores" : [ "com.bbn.akbc.neolearnit.scoring.tables.PatternScoreTable", {
    "data" : [ "com.bbn.akbc.neolearnit.storage.EfficientMapDataStore", {
      "keyList" : [ "java.util.ArrayList", [ [ "com.bbn.akbc.neolearnit.observations.pattern.SerifPattern", {
        "toIDString" : "(mention (return slot0) (headword livestock))",
        "toPrettyString" : " livestock[0]"
      } ], [ "com.bbn.akbc.neolearnit.observations.pattern.SerifPattern", {
        "toIDString" : "(mention (return slot0) (headword cattle))",
        "toPrettyString" : " cattle[0]"
      } ], [ "com.bbn.akbc.neolearnit.observations.pattern.SerifPattern", {
        "toIDString" : "(mention (return slot0) (headword goat))",
        "toPrettyString" : " goat[0]"
      } ], [ "com.bbn.akbc.neolearnit.observations.pattern.SerifPattern", {
        "toIDString" : "(mention (return slot0) (headword pig))",
        "toPrettyString" : " pig[0]"
      } ], [ "com.bbn.akbc.neolearnit.observations.pattern.SerifPattern", {
        "toIDString" : "(mention (return slot0) (headword pigs))",
        "toPrettyString" : " pigs[0]"
      } ], [ "com.bbn.akbc.neolearnit.observations.pattern.SerifPattern", {
        "toIDString" : "(mention (return slot0) (headword horse))",
        "toPrettyString" : " horse[0]"
      } ], [ "com.bbn.akbc.neolearnit.observations.pattern.SerifPattern", {
        "toIDString" : "(mention (return slot0) (headword goats))",
        "toPrettyString" : " goats[0]"
      } ], [ "com.bbn.akbc.neolearnit.observations.pattern.SerifPattern", {
        "toIDString" : "(mention (return slot0) (headword chickens))",
        "toPrettyString" : " chickens[0]"
      } ], [ "com.bbn.akbc.neolearnit.observations.pattern.SerifPattern", {
        "toIDString" : "(mention (return slot0) (headword chicken))",
        "toPrettyString" : " chicken[0]"
      } ], [ "com.bbn.akbc.neolearnit.observations.pattern.SerifPattern", {
        "toIDString" : "(mention (return slot0) (headword horses))",
        "toPrettyString" : " horses[0]"
      } ], [ "com.bbn.akbc.neolearnit.observations.pattern.SerifPattern", {
        "toIDString" : "(mention (return slot0) (headword cow))",
        "toPrettyString" : " cow[0]"
      } ], [ "com.bbn.akbc.neolearnit.observations.pattern.SerifPattern", {
        "toIDString" : "(mention (return slot0) (headword poultry))",
        "toPrettyString" : " poultry[0]"
      } ], [ "com.bbn.akbc.neolearnit.observations.pattern.SerifPattern", {
        "toIDString" : "(mention (return slot0) (headword sheep))",
        "toPrettyString" : " sheep[0]"
      } ], [ "com.bbn.akbc.neolearnit.observations.pattern.SerifPattern", {
        "toIDString" : "(mention (return slot0) (headword cows))",
        "toPrettyString" : " cows[0]"
      } ] ] ],
      "valList" : [ "java.util.ArrayList", [ [ "com.bbn.akbc.neolearnit.scoring.scores.PatternScore", {
        "precision" : 0.95,
        "recall" : 0.01,
        "confidence" : 1.0,
        "confidenceFromSimilarity" : 0.0,
        "confidenceNumerator" : 3159.900000000199,
        "confidenceDenominator" : 3159.900000000199,
        "frequency" : 0,
        "knownFrequency" : 3420,
        "seedFrequency" : 0,
        "knownSeedFrequency" : 0,
        "frozenPatternInstanceCount" : 0,
        "tp" : 3001.905000000189,
        "fp" : 157.9950000000101,
        "fn" : "NaN",
        "tn" : "NaN",
        "frozen" : true,
        "proposed" : false,
        "iteration" : 9,
        "frozenIteration" : 9,
        "sources" : [ "com.bbn.akbc.neolearnit.storage.EfficientMultisetDataStore", {
          "keyList" : [ "java.util.ArrayList", [ ] ],
          "entries" : [ "java.util.ArrayList", [ ] ]
        } ],
        "patternWeightedPrecision" : 0.0,
        "patternPrecision" : 0.0,
        "patternFrequency" : 0.0
      } ], [ "com.bbn.akbc.neolearnit.scoring.scores.PatternScore", {
        "precision" : 0.95,
        "recall" : 0.01,
        "confidence" : 1.0,
        "confidenceFromSimilarity" : 0.0,
        "confidenceNumerator" : 1023.0999999999814,
        "confidenceDenominator" : 1023.0999999999814,
        "frequency" : 0,
        "knownFrequency" : 1121,
        "seedFrequency" : 0,
        "knownSeedFrequency" : 0,
        "frozenPatternInstanceCount" : 0,
        "tp" : 971.9449999999823,
        "fp" : 51.15499999999911,
        "fn" : "NaN",
        "tn" : "NaN",
        "frozen" : true,
        "proposed" : false,
        "iteration" : 9,
        "frozenIteration" : 9,
        "sources" : [ "com.bbn.akbc.neolearnit.storage.EfficientMultisetDataStore", {
          "keyList" : [ "java.util.ArrayList", [ ] ],
          "entries" : [ "java.util.ArrayList", [ ] ]
        } ],
        "patternWeightedPrecision" : 0.0,
        "patternPrecision" : 0.0,
        "patternFrequency" : 0.0
      } ], [ "com.bbn.akbc.neolearnit.scoring.scores.PatternScore", {
        "precision" : 0.95,
        "recall" : 0.01,
        "confidence" : 1.0,
        "confidenceFromSimilarity" : 0.0,
        "confidenceNumerator" : 405.5500000000002,
        "confidenceDenominator" : 405.5500000000002,
        "frequency" : 0,
        "knownFrequency" : 405,
        "seedFrequency" : 0,
        "knownSeedFrequency" : 0,
        "frozenPatternInstanceCount" : 0,
        "tp" : 385.27250000000015,
        "fp" : 20.27750000000003,
        "fn" : "NaN",
        "tn" : "NaN",
        "frozen" : true,
        "proposed" : false,
        "iteration" : 9,
        "frozenIteration" : 9,
        "sources" : [ "com.bbn.akbc.neolearnit.storage.EfficientMultisetDataStore", {
          "keyList" : [ "java.util.ArrayList", [ ] ],
          "entries" : [ "java.util.ArrayList", [ ] ]
        } ],
        "patternWeightedPrecision" : 0.0,
        "patternPrecision" : 0.0,
        "patternFrequency" : 0.0
      } ], [ "com.bbn.akbc.neolearnit.scoring.scores.PatternScore", {
        "precision" : 0.95,
        "recall" : 0.01,
        "confidence" : 1.0,
        "confidenceFromSimilarity" : 0.0,
        "confidenceNumerator" : 10.800000000000002,
        "confidenceDenominator" : 10.800000000000002,
        "frequency" : 0,
        "knownFrequency" : 11,
        "seedFrequency" : 0,
        "knownSeedFrequency" : 0,
        "frozenPatternInstanceCount" : 0,
        "tp" : 10.260000000000002,
        "fp" : 0.5400000000000006,
        "fn" : "NaN",
        "tn" : "NaN",
        "frozen" : true,
        "proposed" : false,
        "iteration" : 9,
        "frozenIteration" : 9,
        "sources" : [ "com.bbn.akbc.neolearnit.storage.EfficientMultisetDataStore", {
          "keyList" : [ "java.util.ArrayList", [ ] ],
          "entries" : [ "java.util.ArrayList", [ ] ]
        } ],
        "patternWeightedPrecision" : 0.0,
        "patternPrecision" : 0.0,
        "patternFrequency" : 0.0
      } ], [ "com.bbn.akbc.neolearnit.scoring.scores.PatternScore", {
        "precision" : 0.95,
        "recall" : 0.01,
        "confidence" : 1.0,
        "confidenceFromSimilarity" : 0.0,
        "confidenceNumerator" : 12.200000000000003,
        "confidenceDenominator" : 12.200000000000003,
        "frequency" : 0,
        "knownFrequency" : 13,
        "seedFrequency" : 0,
        "knownSeedFrequency" : 0,
        "frozenPatternInstanceCount" : 0,
        "tp" : 11.590000000000002,
        "fp" : 0.6100000000000007,
        "fn" : "NaN",
        "tn" : "NaN",
        "frozen" : true,
        "proposed" : false,
        "iteration" : 9,
        "frozenIteration" : 9,
        "sources" : [ "com.bbn.akbc.neolearnit.storage.EfficientMultisetDataStore", {
          "keyList" : [ "java.util.ArrayList", [ ] ],
          "entries" : [ "java.util.ArrayList", [ ] ]
        } ],
        "patternWeightedPrecision" : 0.0,
        "patternPrecision" : 0.0,
        "patternFrequency" : 0.0
      } ], [ "com.bbn.akbc.neolearnit.scoring.scores.PatternScore", {
        "precision" : 0.95,
        "recall" : 0.01,
        "confidence" : 1.0,
        "confidenceFromSimilarity" : 0.0,
        "confidenceNumerator" : 21.699999999999996,
        "confidenceDenominator" : 21.699999999999996,
        "frequency" : 0,
        "knownFrequency" : 23,
        "seedFrequency" : 0,
        "knownSeedFrequency" : 0,
        "frozenPatternInstanceCount" : 0,
        "tp" : 20.614999999999995,
        "fp" : 1.0850000000000009,
        "fn" : "NaN",
        "tn" : "NaN",
        "frozen" : true,
        "proposed" : false,
        "iteration" : 9,
        "frozenIteration" : 9,
        "sources" : [ "com.bbn.akbc.neolearnit.storage.EfficientMultisetDataStore", {
          "keyList" : [ "java.util.ArrayList", [ ] ],
          "entries" : [ "java.util.ArrayList", [ ] ]
        } ],
        "patternWeightedPrecision" : 0.0,
        "patternPrecision" : 0.0,
        "patternFrequency" : 0.0
      } ], [ "com.bbn.akbc.neolearnit.scoring.scores.PatternScore", {
        "precision" : 0.95,
        "recall" : 0.01,
        "confidence" : 1.0,
        "confidenceFromSimilarity" : 0.0,
        "confidenceNumerator" : 547.4000000000004,
        "confidenceDenominator" : 547.4000000000004,
        "frequency" : 0,
        "knownFrequency" : 598,
        "seedFrequency" : 0,
        "knownSeedFrequency" : 0,
        "frozenPatternInstanceCount" : 0,
        "tp" : 520.0300000000004,
        "fp" : 27.370000000000047,
        "fn" : "NaN",
        "tn" : "NaN",
        "frozen" : true,
        "proposed" : false,
        "iteration" : 9,
        "frozenIteration" : 9,
        "sources" : [ "com.bbn.akbc.neolearnit.storage.EfficientMultisetDataStore", {
          "keyList" : [ "java.util.ArrayList", [ ] ],
          "entries" : [ "java.util.ArrayList", [ ] ]
        } ],
        "patternWeightedPrecision" : 0.0,
        "patternPrecision" : 0.0,
        "patternFrequency" : 0.0
      } ], [ "com.bbn.akbc.neolearnit.scoring.scores.PatternScore", {
        "precision" : 0.95,
        "recall" : 0.01,
        "confidence" : 1.0,
        "confidenceFromSimilarity" : 0.0,
        "confidenceNumerator" : 11.000000000000002,
        "confidenceDenominator" : 11.000000000000002,
        "frequency" : 0,
        "knownFrequency" : 12,
        "seedFrequency" : 0,
        "knownSeedFrequency" : 0,
        "frozenPatternInstanceCount" : 0,
        "tp" : 10.450000000000001,
        "fp" : 0.5500000000000006,
        "fn" : "NaN",
        "tn" : "NaN",
        "frozen" : true,
        "proposed" : false,
        "iteration" : 9,
        "frozenIteration" : 9,
        "sources" : [ "com.bbn.akbc.neolearnit.storage.EfficientMultisetDataStore", {
          "keyList" : [ "java.util.ArrayList", [ ] ],
          "entries" : [ "java.util.ArrayList", [ ] ]
        } ],
        "patternWeightedPrecision" : 0.0,
        "patternPrecision" : 0.0,
        "patternFrequency" : 0.0
      } ], [ "com.bbn.akbc.neolearnit.scoring.scores.PatternScore", {
        "precision" : 0.95,
        "recall" : 0.01,
        "confidence" : 1.0,
        "confidenceFromSimilarity" : 0.0,
        "confidenceNumerator" : 35.1,
        "confidenceDenominator" : 35.1,
        "frequency" : 0,
        "knownFrequency" : 35,
        "seedFrequency" : 0,
        "knownSeedFrequency" : 0,
        "frozenPatternInstanceCount" : 0,
        "tp" : 33.345,
        "fp" : 1.7550000000000017,
        "fn" : "NaN",
        "tn" : "NaN",
        "frozen" : true,
        "proposed" : false,
        "iteration" : 9,
        "frozenIteration" : 9,
        "sources" : [ "com.bbn.akbc.neolearnit.storage.EfficientMultisetDataStore", {
          "keyList" : [ "java.util.ArrayList", [ ] ],
          "entries" : [ "java.util.ArrayList", [ ] ]
        } ],
        "patternWeightedPrecision" : 0.0,
        "patternPrecision" : 0.0,
        "patternFrequency" : 0.0
      } ], [ "com.bbn.akbc.neolearnit.scoring.scores.PatternScore", {
        "precision" : 0.95,
        "recall" : 0.01,
        "confidence" : 1.0,
        "confidenceFromSimilarity" : 0.0,
        "confidenceNumerator" : 9.400000000000002,
        "confidenceDenominator" : 9.400000000000002,
        "frequency" : 0,
        "knownFrequency" : 11,
        "seedFrequency" : 0,
        "knownSeedFrequency" : 0,
        "frozenPatternInstanceCount" : 0,
        "tp" : 8.930000000000001,
        "fp" : 0.47000000000000053,
        "fn" : "NaN",
        "tn" : "NaN",
        "frozen" : true,
        "proposed" : false,
        "iteration" : 9,
        "frozenIteration" : 9,
        "sources" : [ "com.bbn.akbc.neolearnit.storage.EfficientMultisetDataStore", {
          "keyList" : [ "java.util.ArrayList", [ ] ],
          "entries" : [ "java.util.ArrayList", [ ] ]
        } ],
        "patternWeightedPrecision" : 0.0,
        "patternPrecision" : 0.0,
        "patternFrequency" : 0.0
      } ], [ "com.bbn.akbc.neolearnit.scoring.scores.PatternScore", {
        "precision" : 0.95,
        "recall" : 0.01,
        "confidence" : 1.0,
        "confidenceFromSimilarity" : 0.0,
        "confidenceNumerator" : 33.59999999999998,
        "confidenceDenominator" : 33.59999999999998,
        "frequency" : 0,
        "knownFrequency" : 36,
        "seedFrequency" : 0,
        "knownSeedFrequency" : 0,
        "frozenPatternInstanceCount" : 0,
        "tp" : 31.91999999999998,
        "fp" : 1.6800000000000006,
        "fn" : "NaN",
        "tn" : "NaN",
        "frozen" : true,
        "proposed" : false,
        "iteration" : 9,
        "frozenIteration" : 9,
        "sources" : [ "com.bbn.akbc.neolearnit.storage.EfficientMultisetDataStore", {
          "keyList" : [ "java.util.ArrayList", [ ] ],
          "entries" : [ "java.util.ArrayList", [ ] ]
        } ],
        "patternWeightedPrecision" : 0.0,
        "patternPrecision" : 0.0,
        "patternFrequency" : 0.0
      } ], [ "com.bbn.akbc.neolearnit.scoring.scores.PatternScore", {
        "precision" : 0.95,
        "recall" : 0.01,
        "confidence" : 1.0,
        "confidenceFromSimilarity" : 0.0,
        "confidenceNumerator" : 132.25000000000026,
        "confidenceDenominator" : 132.25000000000026,
        "frequency" : 0,
        "knownFrequency" : 149,
        "seedFrequency" : 0,
        "knownSeedFrequency" : 0,
        "frozenPatternInstanceCount" : 0,
        "tp" : 125.63750000000023,
        "fp" : 6.6125000000000185,
        "fn" : "NaN",
        "tn" : "NaN",
        "frozen" : true,
        "proposed" : false,
        "iteration" : 9,
        "frozenIteration" : 9,
        "sources" : [ "com.bbn.akbc.neolearnit.storage.EfficientMultisetDataStore", {
          "keyList" : [ "java.util.ArrayList", [ ] ],
          "entries" : [ "java.util.ArrayList", [ ] ]
        } ],
        "patternWeightedPrecision" : 0.0,
        "patternPrecision" : 0.0,
        "patternFrequency" : 0.0
      } ], [ "com.bbn.akbc.neolearnit.scoring.scores.PatternScore", {
        "precision" : 0.95,
        "recall" : 0.01,
        "confidence" : 1.0,
        "confidenceFromSimilarity" : 0.0,
        "confidenceNumerator" : 618.8499999999996,
        "confidenceDenominator" : 618.8499999999996,
        "frequency" : 0,
        "knownFrequency" : 655,
        "seedFrequency" : 0,
        "knownSeedFrequency" : 0,
        "frozenPatternInstanceCount" : 0,
        "tp" : 587.9074999999996,
        "fp" : 30.942500000000006,
        "fn" : "NaN",
        "tn" : "NaN",
        "frozen" : true,
        "proposed" : false,
        "iteration" : 9,
        "frozenIteration" : 9,
        "sources" : [ "com.bbn.akbc.neolearnit.storage.EfficientMultisetDataStore", {
          "keyList" : [ "java.util.ArrayList", [ ] ],
          "entries" : [ "java.util.ArrayList", [ ] ]
        } ],
        "patternWeightedPrecision" : 0.0,
        "patternPrecision" : 0.0,
        "patternFrequency" : 0.0
      } ], [ "com.bbn.akbc.neolearnit.scoring.scores.PatternScore", {
        "precision" : 0.95,
        "recall" : 0.01,
        "confidence" : 1.0,
        "confidenceFromSimilarity" : 0.0,
        "confidenceNumerator" : 45.94999999999997,
        "confidenceDenominator" : 45.94999999999997,
        "frequency" : 0,
        "knownFrequency" : 52,
        "seedFrequency" : 0,
        "knownSeedFrequency" : 0,
        "frozenPatternInstanceCount" : 0,
        "tp" : 43.65249999999997,
        "fp" : 2.2975000000000003,
        "fn" : "NaN",
        "tn" : "NaN",
        "frozen" : true,
        "proposed" : false,
        "iteration" : 9,
        "frozenIteration" : 9,
        "sources" : [ "com.bbn.akbc.neolearnit.storage.EfficientMultisetDataStore", {
          "keyList" : [ "java.util.ArrayList", [ ] ],
          "entries" : [ "java.util.ArrayList", [ ] ]
        } ],
        "patternWeightedPrecision" : 0.0,
        "patternPrecision" : 0.0,
        "patternFrequency" : 0.0
      } ] ] ],
      "entries" : [ "java.util.ArrayList", [ [ "com.bbn.akbc.neolearnit.storage.EfficientMapDataStore$MappedEntry", {
        "key" : 0,
        "value" : 0
      } ], [ "com.bbn.akbc.neolearnit.storage.EfficientMapDataStore$MappedEntry", {
        "key" : 1,
        "value" : 1
      } ], [ "com.bbn.akbc.neolearnit.storage.EfficientMapDataStore$MappedEntry", {
        "key" : 2,
        "value" : 2
      } ], [ "com.bbn.akbc.neolearnit.storage.EfficientMapDataStore$MappedEntry", {
        "key" : 3,
        "value" : 3
      } ], [ "com.bbn.akbc.neolearnit.storage.EfficientMapDataStore$MappedEntry", {
        "key" : 4,
        "value" : 4
      } ], [ "com.bbn.akbc.neolearnit.storage.EfficientMapDataStore$MappedEntry", {
        "key" : 5,
        "value" : 5
      } ], [ "com.bbn.akbc.neolearnit.storage.EfficientMapDataStore$MappedEntry", {
        "key" : 6,
        "value" : 6
      } ], [ "com.bbn.akbc.neolearnit.storage.EfficientMapDataStore$MappedEntry", {
        "key" : 7,
        "value" : 7
      } ], [ "com.bbn.akbc.neolearnit.storage.EfficientMapDataStore$MappedEntry", {
        "key" : 8,
        "value" : 8
      } ], [ "com.bbn.akbc.neolearnit.storage.EfficientMapDataStore$MappedEntry", {
        "key" : 9,
        "value" : 9
      } ], [ "com.bbn.akbc.neolearnit.storage.EfficientMapDataStore$MappedEntry", {
        "key" : 10,
        "value" : 10
      } ], [ "com.bbn.akbc.neolearnit.storage.EfficientMapDataStore$MappedEntry", {
        "key" : 11,
        "value" : 11
      } ], [ "com.bbn.akbc.neolearnit.storage.EfficientMapDataStore$MappedEntry", {
        "key" : 12,
        "value" : 12
      } ], [ "com.bbn.akbc.neolearnit.storage.EfficientMapDataStore$MappedEntry", {
        "key" : 13,
        "value" : 13
      } ] ] ]
    } ],
    "iteration" : 32
  } ],
  "tripleScores" : [ "com.bbn.akbc.neolearnit.scoring.tables.TripleScoreTable", {
    "data" : [ "com.bbn.akbc.neolearnit.storage.EfficientMapDataStore", {
      "keyList" : [ "java.util.ArrayList", [ ] ],
      "valList" : [ "java.util.ArrayList", [ ] ],
      "entries" : [ "java.util.ArrayList", [ ] ]
    } ],
    "iteration" : 0
  } ],
  "iteration" : 32,
  "goodSeedPrior" : "Infinity",
  "totalConfidenceDenominator" : 0.0,
  "stage" : "initial",
  "params" : null,
  "experimentName" : "default"
} ]