[ "com.bbn.akbc.neolearnit.scoring.TargetAndScoreTables", {
  "startDate" : [ "java.util.Date", 1595101572814 ],
  "seedScores" : [ "com.bbn.akbc.neolearnit.scoring.tables.SeedScoreTable", {
    "data" : [ "com.bbn.akbc.neolearnit.storage.EfficientMapDataStore", {
      "keyList" : [ "java.util.ArrayList", [ ] ],
      "valList" : [ "java.util.ArrayList", [ ] ],
      "entries" : [ "java.util.ArrayList", [ ] ]
    } ],
    "iteration" : 21
  } ],
  "patternScores" : [ "com.bbn.akbc.neolearnit.scoring.tables.PatternScoreTable", {
    "data" : [ "com.bbn.akbc.neolearnit.storage.EfficientMapDataStore", {
      "keyList" : [ "java.util.ArrayList", [ [ "com.bbn.akbc.neolearnit.observations.pattern.SerifPattern", {
        "toIDString" : "(mention (return slot0) (headword warfare) (regex (regex (re (text (string \"maritime\"))))))",
        "toPrettyString" : " maritime warfare[0]"
      } ], [ "com.bbn.akbc.neolearnit.observations.pattern.SerifPattern", {
        "toIDString" : "(mention (return slot0) (headword exercises) (regex (regex (re (text (string \"naval\"))))))",
        "toPrettyString" : " naval exercises[0]"
      } ], [ "com.bbn.akbc.neolearnit.observations.pattern.SerifPattern", {
        "toIDString" : "(mention (return slot0) (headword blockade) (regex (regex (re (text (string \"naval\"))))))",
        "toPrettyString" : " naval blockade[0]"
      } ], [ "com.bbn.akbc.neolearnit.observations.pattern.SerifPattern", {
        "toIDString" : "(nprop (return slot0) (predicate hijacking) (args (argument (role of) (mention (headword sea) (acetype LOC))) (argument (role <ref>) (mention (headword hijacking) (acetype OTH)))))",
        "toPrettyString" : " [ [n]hijacking[0] of sea[LOC] ]"
      } ], [ "com.bbn.akbc.neolearnit.observations.pattern.SerifPattern", {
        "toIDString" : "(mention (return slot0) (headword trials) (regex (regex (re (text (string \"sea\"))))))",
        "toPrettyString" : " sea trials[0]"
      } ], [ "com.bbn.akbc.neolearnit.observations.pattern.SerifPattern", {
        "toIDString" : "(mention (return slot0) (headword awareness) (regex (regex (re (text (string \"maritime\"))))))",
        "toPrettyString" : " maritime awareness[0]"
      } ], [ "com.bbn.akbc.neolearnit.observations.pattern.SerifPattern", {
        "toIDString" : "(vprop (return slot0) (predicate intercepted) (args (argument (role over) (mention (headword sea) (acetype LOC)))))",
        "toPrettyString" : " [ [v]intercepted[0] over sea[LOC] ]"
      } ], [ "com.bbn.akbc.neolearnit.observations.pattern.SerifPattern", {
        "toIDString" : "(mention (return slot0) (headword exercise) (regex (regex (re (text (string \"naval\"))))))",
        "toPrettyString" : " naval exercise[0]"
      } ], [ "com.bbn.akbc.neolearnit.observations.pattern.SerifPattern", {
        "toIDString" : "(mention (return slot0) (headword warfare) (regex (regex (re (text (string \"maritime hybrid\"))))))",
        "toPrettyString" : " maritime hybrid warfare[0]"
      } ], [ "com.bbn.akbc.neolearnit.observations.pattern.SerifPattern", {
        "toIDString" : "(mention (return slot0) (headword strategy) (regex (regex (re (text (string \"naval\"))))))",
        "toPrettyString" : " naval strategy[0]"
      } ] ] ],
      "valList" : [ "java.util.ArrayList", [ [ "com.bbn.akbc.neolearnit.scoring.scores.PatternScore", {
        "precision" : 0.95,
        "recall" : 0.01,
        "confidence" : 1.0,
        "confidenceFromSimilarity" : 0.0,
        "confidenceNumerator" : 4.0,
        "confidenceDenominator" : 4.0,
        "frequency" : 4,
        "knownFrequency" : 4,
        "seedFrequency" : 0,
        "knownSeedFrequency" : 0,
        "frozenPatternInstanceCount" : 0,
        "tp" : 3.8,
        "fp" : 0.20000000000000018,
        "fn" : "NaN",
        "tn" : "NaN",
        "frozen" : true,
        "proposed" : false,
        "iteration" : 0,
        "frozenIteration" : 0,
        "sources" : [ "com.bbn.akbc.neolearnit.storage.EfficientMultisetDataStore", {
          "keyList" : [ "java.util.ArrayList", [ ] ],
          "entries" : [ "java.util.ArrayList", [ ] ]
        } ],
        "patternWeightedPrecision" : 0.0,
        "patternPrecision" : 0.0,
        "patternFrequency" : 0.0
      } ], [ "com.bbn.akbc.neolearnit.scoring.scores.PatternScore", {
        "precision" : 0.95,
        "recall" : 0.01,
        "confidence" : 1.0,
        "confidenceFromSimilarity" : 0.0,
        "confidenceNumerator" : 2.0,
        "confidenceDenominator" : 2.0,
        "frequency" : 2,
        "knownFrequency" : 2,
        "seedFrequency" : 0,
        "knownSeedFrequency" : 0,
        "frozenPatternInstanceCount" : 0,
        "tp" : 1.9,
        "fp" : 0.10000000000000009,
        "fn" : "NaN",
        "tn" : "NaN",
        "frozen" : true,
        "proposed" : false,
        "iteration" : 20,
        "frozenIteration" : 20,
        "sources" : [ "com.bbn.akbc.neolearnit.storage.EfficientMultisetDataStore", {
          "keyList" : [ "java.util.ArrayList", [ ] ],
          "entries" : [ "java.util.ArrayList", [ ] ]
        } ],
        "patternWeightedPrecision" : 0.0,
        "patternPrecision" : 0.0,
        "patternFrequency" : 0.0
      } ], [ "com.bbn.akbc.neolearnit.scoring.scores.PatternScore", {
        "precision" : 0.95,
        "recall" : 0.01,
        "confidence" : 1.0,
        "confidenceFromSimilarity" : 0.0,
        "confidenceNumerator" : 13.0,
        "confidenceDenominator" : 13.0,
        "frequency" : 13,
        "knownFrequency" : 12,
        "seedFrequency" : 0,
        "knownSeedFrequency" : 0,
        "frozenPatternInstanceCount" : 0,
        "tp" : 12.35,
        "fp" : 0.6500000000000006,
        "fn" : "NaN",
        "tn" : "NaN",
        "frozen" : true,
        "proposed" : false,
        "iteration" : 20,
        "frozenIteration" : 20,
        "sources" : [ "com.bbn.akbc.neolearnit.storage.EfficientMultisetDataStore", {
          "keyList" : [ "java.util.ArrayList", [ ] ],
          "entries" : [ "java.util.ArrayList", [ ] ]
        } ],
        "patternWeightedPrecision" : 0.0,
        "patternPrecision" : 0.0,
        "patternFrequency" : 0.0
      } ], [ "com.bbn.akbc.neolearnit.scoring.scores.PatternScore", {
        "precision" : 0.05,
        "recall" : 0.01,
        "confidence" : 1.0,
        "confidenceFromSimilarity" : 0.0,
        "confidenceNumerator" : 43.0,
        "confidenceDenominator" : 43.0,
        "frequency" : 43,
        "knownFrequency" : 2,
        "seedFrequency" : 0,
        "knownSeedFrequency" : 0,
        "frozenPatternInstanceCount" : 0,
        "tp" : 2.15,
        "fp" : 40.85,
        "fn" : "NaN",
        "tn" : "NaN",
        "frozen" : true,
        "proposed" : false,
        "iteration" : 0,
        "frozenIteration" : 0,
        "sources" : [ "com.bbn.akbc.neolearnit.storage.EfficientMultisetDataStore", {
          "keyList" : [ "java.util.ArrayList", [ ] ],
          "entries" : [ "java.util.ArrayList", [ ] ]
        } ],
        "patternWeightedPrecision" : 0.0,
        "patternPrecision" : 0.0,
        "patternFrequency" : 0.0
      } ], [ "com.bbn.akbc.neolearnit.scoring.scores.PatternScore", {
        "precision" : 0.95,
        "recall" : 0.01,
        "confidence" : 1.0,
        "confidenceFromSimilarity" : 0.0,
        "confidenceNumerator" : 22.0,
        "confidenceDenominator" : 22.0,
        "frequency" : 22,
        "knownFrequency" : 21,
        "seedFrequency" : 0,
        "knownSeedFrequency" : 0,
        "frozenPatternInstanceCount" : 0,
        "tp" : 20.9,
        "fp" : 1.100000000000001,
        "fn" : "NaN",
        "tn" : "NaN",
        "frozen" : true,
        "proposed" : false,
        "iteration" : 0,
        "frozenIteration" : 0,
        "sources" : [ "com.bbn.akbc.neolearnit.storage.EfficientMultisetDataStore", {
          "keyList" : [ "java.util.ArrayList", [ ] ],
          "entries" : [ "java.util.ArrayList", [ ] ]
        } ],
        "patternWeightedPrecision" : 0.0,
        "patternPrecision" : 0.0,
        "patternFrequency" : 0.0
      } ], [ "com.bbn.akbc.neolearnit.scoring.scores.PatternScore", {
        "precision" : 0.95,
        "recall" : 0.01,
        "confidence" : 1.0,
        "confidenceFromSimilarity" : 0.0,
        "confidenceNumerator" : 10.0,
        "confidenceDenominator" : 10.0,
        "frequency" : 10,
        "knownFrequency" : 10,
        "seedFrequency" : 0,
        "knownSeedFrequency" : 0,
        "frozenPatternInstanceCount" : 0,
        "tp" : 9.5,
        "fp" : 0.5000000000000004,
        "fn" : "NaN",
        "tn" : "NaN",
        "frozen" : true,
        "proposed" : false,
        "iteration" : 20,
        "frozenIteration" : 20,
        "sources" : [ "com.bbn.akbc.neolearnit.storage.EfficientMultisetDataStore", {
          "keyList" : [ "java.util.ArrayList", [ ] ],
          "entries" : [ "java.util.ArrayList", [ ] ]
        } ],
        "patternWeightedPrecision" : 0.0,
        "patternPrecision" : 0.0,
        "patternFrequency" : 0.0
      } ], [ "com.bbn.akbc.neolearnit.scoring.scores.PatternScore", {
        "precision" : 0.05,
        "recall" : 0.01,
        "confidence" : 1.0,
        "confidenceFromSimilarity" : 0.0,
        "confidenceNumerator" : 13.0,
        "confidenceDenominator" : 13.0,
        "frequency" : 13,
        "knownFrequency" : 1,
        "seedFrequency" : 0,
        "knownSeedFrequency" : 0,
        "frozenPatternInstanceCount" : 0,
        "tp" : 0.65,
        "fp" : 12.35,
        "fn" : "NaN",
        "tn" : "NaN",
        "frozen" : true,
        "proposed" : false,
        "iteration" : 0,
        "frozenIteration" : 0,
        "sources" : [ "com.bbn.akbc.neolearnit.storage.EfficientMultisetDataStore", {
          "keyList" : [ "java.util.ArrayList", [ ] ],
          "entries" : [ "java.util.ArrayList", [ ] ]
        } ],
        "patternWeightedPrecision" : 0.0,
        "patternPrecision" : 0.0,
        "patternFrequency" : 0.0
      } ], [ "com.bbn.akbc.neolearnit.scoring.scores.PatternScore", {
        "precision" : 0.95,
        "recall" : 0.01,
        "confidence" : 1.0,
        "confidenceFromSimilarity" : 0.0,
        "confidenceNumerator" : 2.0,
        "confidenceDenominator" : 2.0,
        "frequency" : 2,
        "knownFrequency" : 2,
        "seedFrequency" : 0,
        "knownSeedFrequency" : 0,
        "frozenPatternInstanceCount" : 0,
        "tp" : 1.9,
        "fp" : 0.10000000000000009,
        "fn" : "NaN",
        "tn" : "NaN",
        "frozen" : true,
        "proposed" : false,
        "iteration" : 20,
        "frozenIteration" : 20,
        "sources" : [ "com.bbn.akbc.neolearnit.storage.EfficientMultisetDataStore", {
          "keyList" : [ "java.util.ArrayList", [ ] ],
          "entries" : [ "java.util.ArrayList", [ ] ]
        } ],
        "patternWeightedPrecision" : 0.0,
        "patternPrecision" : 0.0,
        "patternFrequency" : 0.0
      } ], [ "com.bbn.akbc.neolearnit.scoring.scores.PatternScore", {
        "precision" : 0.95,
        "recall" : 0.01,
        "confidence" : 1.0,
        "confidenceFromSimilarity" : 0.0,
        "confidenceNumerator" : 4.0,
        "confidenceDenominator" : 4.0,
        "frequency" : 4,
        "knownFrequency" : 4,
        "seedFrequency" : 0,
        "knownSeedFrequency" : 0,
        "frozenPatternInstanceCount" : 0,
        "tp" : 3.8,
        "fp" : 0.20000000000000018,
        "fn" : "NaN",
        "tn" : "NaN",
        "frozen" : true,
        "proposed" : false,
        "iteration" : 0,
        "frozenIteration" : 0,
        "sources" : [ "com.bbn.akbc.neolearnit.storage.EfficientMultisetDataStore", {
          "keyList" : [ "java.util.ArrayList", [ ] ],
          "entries" : [ "java.util.ArrayList", [ ] ]
        } ],
        "patternWeightedPrecision" : 0.0,
        "patternPrecision" : 0.0,
        "patternFrequency" : 0.0
      } ], [ "com.bbn.akbc.neolearnit.scoring.scores.PatternScore", {
        "precision" : 0.95,
        "recall" : 0.01,
        "confidence" : 1.0,
        "confidenceFromSimilarity" : 0.0,
        "confidenceNumerator" : 1.0,
        "confidenceDenominator" : 1.0,
        "frequency" : 1,
        "knownFrequency" : 1,
        "seedFrequency" : 0,
        "knownSeedFrequency" : 0,
        "frozenPatternInstanceCount" : 0,
        "tp" : 0.95,
        "fp" : 0.050000000000000044,
        "fn" : "NaN",
        "tn" : "NaN",
        "frozen" : true,
        "proposed" : false,
        "iteration" : 20,
        "frozenIteration" : 20,
        "sources" : [ "com.bbn.akbc.neolearnit.storage.EfficientMultisetDataStore", {
          "keyList" : [ "java.util.ArrayList", [ ] ],
          "entries" : [ "java.util.ArrayList", [ ] ]
        } ],
        "patternWeightedPrecision" : 0.0,
        "patternPrecision" : 0.0,
        "patternFrequency" : 0.0
      } ] ] ],
      "entries" : [ "java.util.ArrayList", [ [ "com.bbn.akbc.neolearnit.storage.EfficientMapDataStore$MappedEntry", {
        "key" : 0,
        "value" : 0
      } ], [ "com.bbn.akbc.neolearnit.storage.EfficientMapDataStore$MappedEntry", {
        "key" : 1,
        "value" : 1
      } ], [ "com.bbn.akbc.neolearnit.storage.EfficientMapDataStore$MappedEntry", {
        "key" : 2,
        "value" : 2
      } ], [ "com.bbn.akbc.neolearnit.storage.EfficientMapDataStore$MappedEntry", {
        "key" : 3,
        "value" : 3
      } ], [ "com.bbn.akbc.neolearnit.storage.EfficientMapDataStore$MappedEntry", {
        "key" : 4,
        "value" : 4
      } ], [ "com.bbn.akbc.neolearnit.storage.EfficientMapDataStore$MappedEntry", {
        "key" : 5,
        "value" : 5
      } ], [ "com.bbn.akbc.neolearnit.storage.EfficientMapDataStore$MappedEntry", {
        "key" : 6,
        "value" : 6
      } ], [ "com.bbn.akbc.neolearnit.storage.EfficientMapDataStore$MappedEntry", {
        "key" : 7,
        "value" : 7
      } ], [ "com.bbn.akbc.neolearnit.storage.EfficientMapDataStore$MappedEntry", {
        "key" : 8,
        "value" : 8
      } ], [ "com.bbn.akbc.neolearnit.storage.EfficientMapDataStore$MappedEntry", {
        "key" : 9,
        "value" : 9
      } ] ] ]
    } ],
    "iteration" : 21
  } ],
  "tripleScores" : [ "com.bbn.akbc.neolearnit.scoring.tables.TripleScoreTable", {
    "data" : [ "com.bbn.akbc.neolearnit.storage.EfficientMapDataStore", {
      "keyList" : [ "java.util.ArrayList", [ ] ],
      "valList" : [ "java.util.ArrayList", [ ] ],
      "entries" : [ "java.util.ArrayList", [ ] ]
    } ],
    "iteration" : 0
  } ],
  "iteration" : 21,
  "goodSeedPrior" : "Infinity",
  "totalConfidenceDenominator" : 0.0,
  "stage" : "initial",
  "params" : null,
  "experimentName" : "default"
} ]